{
  "Room": [
    {
      "id": "0",
      "number": "1A",
      "type": "Old",
      "qty": "4",
      "date": "01/12/2023",      
      "roomcharge": "1500000",
      "wifi": true,
      "cable": true
    },
    {
      "id": "1",
      "number": "2A",
      "type": "Old",
      "qty": "4",
      "date": "01/12/2023",      
      "roomcharge": "1500000",
      "wifi": true,
      "cable": true
    },
    {
      "id": "2",
      "number": "3A",
      "type": "Old",
      "qty": "4",
      "date": "01/12/2023",      
      "roomcharge": "1500000",
      "wifi": true,
      "cable": true
    },
    {
      "id": "3",
      "number": "4A",
      "type": "Old",
      "qty": "4",
      "date": "01/12/2023",      
      "roomcharge": "1500000",
      "wifi": true,
      "cable": true
    },
    {
      "id": "4",
      "number": "1B",
      "type": "New",
      "qty": "4",
      "date": "01/12/2023",      
      "roomcharge": "1500000",
      "wifi": true,
      "cable": true
    },
    {
      "id": "5",
      "number": "2B",
      "type": "Old",
      "qty": "4",
      "date": "01/12/2023",      
      "roomcharge": "1500000",
      "wifi": true,
      "cable": true
    },
    {
      "id": "6",
      "number": "3B",
      "type": "Old",
      "qty": "4",
      "date": "01/12/2023",      
      "roomcharge": "1500000",
      "wifi": true,
      "cable": false
    },
    {
      "id": "7",
      "number": "4B",
      "type": "Old",
      "qty": "4",
      "date": "01/12/2023",      
      "roomcharge": "1500000",
      "wifi": true,
      "cable": false
    },
    {
      "number": "6H",
      "type": "Dãy A",
      "qty": "0",
      "date": "2024-02-17",
      "roomcharge": "2000000",
      "wifi": "true",
      "cable": false,
      "id": "Hr727yG"
    }
  ],
  "Profile":[
    {
      "id": "0",
      "room":"1A",
      "name": "Nguyễn Văn A",
      "birth": "1991",
      "location": "Quảng Ngãi",
      "sex": "Nam",
      "cccd": "025421428",
      "sdt": "0908799042",
      "work": "Công nhân"
    },
    {
      "id": "1",
      "room":"1A",
      "name": "Nguyễn Thị A1",
      "birth": "1992",
      "location": "Quảng Ngãi",
      "sex": "Nữ",
      "cccd": "025421428",
      "sdt": "0908799042",
      "work": "Nội trợ"
    },
    {
      "id": "2",
      "room":"2A",
      "name": "Nguyễn Văn A2",
      "birth": "1993",
      "location": "Quảng Ngãi",
      "sex": "Nam",
      "cccd": "025421428",
      "sdt": "0908799042",
      "work": "Nhân viên"
    },
    {
      "id": "3",
      "room":"2A",
      "name": "Nguyễn Văn A3",
      "birth": "1994",
      "location": "Quảng Ngãi",
      "sex": "Nữ",
      "cccd": "025421428",
      "sdt": "0908799042",
      "work": "Sinh viên"
    }
  ]
}